swiftemulator/__init__.py
swiftemulator/__version__.py
swiftemulator/backend/__init__.py
swiftemulator/backend/emulator_generator.py
swiftemulator/backend/model_parameters.py
swiftemulator/backend/model_specification.py
swiftemulator/backend/model_values.py
swiftemulator/comparison/__init__.py
swiftemulator/comparison/penalty.py
swiftemulator/comparison/visualisation.py
swiftemulator/design/__init__.py
swiftemulator/design/latin.py
swiftemulator/design/random.py
swiftemulator/design/transform.py
swiftemulator/emulators/__init__.py
swiftemulator/emulators/base.py
swiftemulator/emulators/gaussian_process.py
swiftemulator/emulators/gaussian_process_bins.py
swiftemulator/emulators/gaussian_process_mcmc.py
swiftemulator/emulators/gaussian_process_one_dim.py
swiftemulator/emulators/linear_model.py
swiftemulator/emulators/multi_gaussian_process.py
swiftemulator/io/__init__.py
swiftemulator/io/swift.py
swiftemulator/mean_models/__init__.py
swiftemulator/mean_models/base.py
swiftemulator/mean_models/fixed.py
swiftemulator/mean_models/linear.py
swiftemulator/mean_models/offset.py
swiftemulator/mean_models/polynomial.py
swiftemulator/mocking/__init__.py
swiftemulator/sensitivity/__init__.py
swiftemulator/sensitivity/basic.py
swiftemulator/sensitivity/cross_check.py
swiftemulator/sensitivity/cross_check_bins.py
swiftemulator-1.3.1.dist-info/licenses/COPYING
swiftemulator-1.3.1.dist-info/licenses/COPYING.LESSER
swiftemulator-1.3.1.dist-info/METADATA
swiftemulator-1.3.1.dist-info/WHEEL
swiftemulator-1.3.1.dist-info/top_level.txt
swiftemulator-1.3.1.dist-info/RECORD
