Metadata-Version: 2.4
Name: swiftemulator
Version: 1.3.1
Summary: Gaussian process emulator for creating synthetic model data across high dimensional parameter spaces, initially developed for use with the SWIFT simulation code.
Home-page: https://github.com/SWIFTSIM/emulator
Author: Josh Borrow
Author-email: josh@joshborrow.com
Classifier: Programming Language :: Python :: 3.6
Classifier: Programming Language :: Python :: 3.7
Classifier: Programming Language :: Python :: 3.8
Classifier: Programming Language :: Python :: 3.9
Classifier: Programming Language :: Python :: 3.10
Classifier: License :: OSI Approved :: GNU Lesser General Public License v3 or later (LGPLv3+)
Classifier: Operating System :: OS Independent
License-File: COPYING
License-File: COPYING.LESSER
Requires-Dist: numpy
Requires-Dist: unyt
Requires-Dist: attrs
Requires-Dist: george
Requires-Dist: SALib
Requires-Dist: scikit-learn
Requires-Dist: corner
Requires-Dist: velociraptor
Requires-Dist: pyyaml
Requires-Dist: pyDOE
Requires-Dist: tqdm
Requires-Dist: emcee
Dynamic: author
Dynamic: author-email
Dynamic: classifier
Dynamic: description
Dynamic: description-content-type
Dynamic: home-page
Dynamic: license-file
Dynamic: requires-dist
Dynamic: summary
